<annotation>
	<folder>train</folder>
	<filename>364.png</filename>
	<path>/home/dell/object_detection_demo/data/images/train/364.png</path>
	<source>
		<database>Unknown</database>
	</source>
	<size>
		<width>800</width>
		<height>600</height>
		<depth>3</depth>
	</size>
	<segmented>0</segmented>
	<object>
		<name>coconut</name>
		<pose>Unspecified</pose>
		<truncated>0</truncated>
		<difficult>0</difficult>
		<bndbox>
			<xmin>260</xmin>
			<ymin>186</ymin>
			<xmax>273</xmax>
			<ymax>198</ymax>
		</bndbox>
	</object>
</annotation>
